webpageshot/__init__.py
webpageshot/converter.py
webpageshot-0.2.dist-info/METADATA
webpageshot-0.2.dist-info/RECORD
webpageshot-0.2.dist-info/WHEEL
webpageshot-0.2.dist-info/entry_points.txt
webpageshot-0.2.dist-info/top_level.txt
