Metadata-Version: 2.1
Name: webpageshot
Version: 0.2
Summary: take screenshot of webpage 
Home-page: https://github.com/pythonml/webpageshot
Author: Zhongqiang Shen
Author-email: shenzhongqiang@msn.com
License: UNKNOWN
Platform: UNKNOWN
Classifier: Programming Language :: Python :: 3
Classifier: License :: OSI Approved :: MIT License
Classifier: Operating System :: OS Independent
Requires-Dist: selenium (>=3.12.0)
